Pmod-I2S2-Arty-A7-35.srcs/sources_1/new/sine_generator.sv


module sine_generator #(
		parameter WIDTH = 7,
		parameter FREQ_STEP = 11
	)(
		input clk,
		input rst_n,

		output [WIDTH-1:0] out
	);

	logic [WIDTH-1:0] out;
	logic [WIDTH-1:0] cnt;

	logic [WIDTH-1:0] sine_table[0:255];

	initial begin
		$readmemh("sine_data.hex", sine_table);
	end

	reg [31:0]	phase;

	always @(posedge clk, negedge rst_n) begin

		if (!rst_n) begin
			out <= 0;
			cnt <= 0;
			phase <= 0;
		end else begin
			cnt <= cnt + 1;
			// out <= sine_table[phase[31:24]];
			out <= sine_table[phase[11:4]];
			phase <= phase + FREQ_STEP;
		end

	end

endmodule : sine_generator

Pmod-I2S2-Arty-A7-35.srcs/sources_1/imports/hdl/axis_volume_controller.v
`timescale 1ns / 1ps
`default_nettype none
//////////////////////////////////////////////////////////////////////////////////
// Company: Digilent
// Engineer: Arthur Brown
// 
// Create Date: 03/23/2018 01:23:15 PM
// Module Name: axis_volume_controller
// Description: AXI-Stream volume controller intended for use with AXI Stream Pmod I2S2 controller.
//              Whenever a 2-word packet is received on the slave interface, it is multiplied by 
//              the value of the switches, taken to represent the range 0.0:1.0, then sent over the
//              master interface. Reception of data on the slave interface is halted while processing and
//              transfer is taking place.
// 
// Revision:
// Revision 0.01 - File Created
// Additional Comments:
// 
//////////////////////////////////////////////////////////////////////////////////

module axis_volume_controller #(
    parameter SWITCH_WIDTH = 4, // WARNING: this module has not been tested with other values of SWITCH_WIDTH, it will likely need some changes
    parameter DATA_WIDTH = 24
) (
    input wire clk,
    input wire rst_n,
    input wire [SWITCH_WIDTH-1:0] sw,
    
    //AXIS SLAVE INTERFACE
    input  wire [DATA_WIDTH-1:0] s_axis_data,
    input  wire s_axis_valid,
    output reg  s_axis_ready = 1'b1,
    input  wire s_axis_last,
    
    // AXIS MASTER INTERFACE
    output reg [DATA_WIDTH-1:0] m_axis_data = 1'b0,
    output reg m_axis_valid = 1'b0,
    input  wire m_axis_ready,
    output reg m_axis_last = 1'b0
);
    localparam MULTIPLIER_WIDTH = 24;
    reg [MULTIPLIER_WIDTH+DATA_WIDTH-1:0] data [1:0];
    reg [MULTIPLIER_WIDTH+DATA_WIDTH-1:0] limit_data [1:0];
        
    reg [SWITCH_WIDTH-1:0] sw_sync_r [2:0];
    wire [SWITCH_WIDTH-1:0] sw_sync = sw_sync_r[2];
//    wire [SWITCH_WIDTH:0] m = {1'b0, sw_sync} + 1;
    reg [MULTIPLIER_WIDTH:0] multiplier = 'b0; // range of 0x00:0x10 for width=4
    
    wire m_select = m_axis_last;
    wire m_new_word = (m_axis_valid == 1'b1 && m_axis_ready == 1'b1) ? 1'b1 : 1'b0;
    wire m_new_packet = (m_new_word == 1'b1 && m_axis_last == 1'b1) ? 1'b1 : 1'b0;
    
    wire s_select = s_axis_last;
    wire s_new_word = (s_axis_valid == 1'b1 && s_axis_ready == 1'b1) ? 1'b1 : 1'b0;
    wire s_new_packet = (s_new_word == 1'b1 && s_axis_last == 1'b1) ? 1'b1 : 1'b0;
    reg s_new_packet_r = 1'b0;
    reg s_new_packet_r_q = 1'b0;
    
    wire [DATA_WIDTH-1:0] limit;
    wire [DATA_WIDTH-1:0] data_out;
    reg [DATA_WIDTH-1:0] m_axis_data_d;
    wire [DATA_WIDTH-1:0] m_axis_data_w;
    reg m_axis_valid_d;
    assign limit = sw_sync[SWITCH_WIDTH-1:0];
    
//    limiter_if limiter_if0();
    
//    assign limiter_if0.clock = clk;
//    assign limiter_if0.rst_n = rst_n;
//    assign limiter_if0.limit = limit;
//    assign limiter_if0.data_in = m_axis_data;
//    assign limiter_if0.data_out = data_out;
    
    // limiter #(DATA_WIDTH) limiter0(clk, rst_n, 1'b1, limit, 1'b1, data[0][DATA_WIDTH-1:0], data_out);

    wire [6:0] sine_out;
    sine_generator sine_generator0(clk, rst_n, sine_out);
    
//    always @(posedge clk) begin
//        m_axis_data <= m_axis_data_w;
//    end
    
    
    always@(posedge clk) begin
        sw_sync_r[2] <= sw_sync_r[1];
        sw_sync_r[1] <= sw_sync_r[0];
        sw_sync_r[0] <= sw;
        
        
//        if (&sw_sync == 1'b1)
//            multiplier <= {1'b1, {MULTIPLIER_WIDTH{1'b0}}};
//        else
            // multiplier <= {1'b0, sw, {MULTIPLIER_WIDTH-SWITCH_WIDTH{1'b0}}} + 1;
//            multiplier <= {sw_sync,{MULTIPLIER_WIDTH{1'b0}}} / {SWITCH_WIDTH{1'b1}};
            multiplier <= {sw_sync,{MULTIPLIER_WIDTH{1'b0}}} / {SWITCH_WIDTH{1'b1}};
            
        s_new_packet_r <= s_new_packet;
        s_new_packet_r_q <= s_new_packet_r;
        
//        m_axis_valid <= m_axis_valid_d;
        
        limit_data[0] <= data_out;
    end
    
    always@(posedge clk)
        if (s_new_word == 1'b1) // sign extend and register AXIS slave data
            data[s_select] <= {{MULTIPLIER_WIDTH{s_axis_data[DATA_WIDTH-1]}}, s_axis_data};
        else if (s_new_packet_r == 1'b1) begin
//            data[0] <= $signed(data[0]) * multiplier << 5; // core volume control algorithm, infers a DSP48 slice
//            data[1] <= $signed(data[1]) * multiplier << 5;
            
//            data[0] <= $signed(data[0]); // core volume control algorithm, infers a DSP48 slice
//            data[1] <= $signed(data[1]);
        end
        
    always@(posedge clk)
        if (s_new_packet_r == 1'b1)
            m_axis_valid <= 1'b1;
        else if (m_new_packet == 1'b1)
            m_axis_valid <= 1'b0;
            
    always@(posedge clk)
        if (m_new_packet == 1'b1)
            m_axis_last <= 1'b0;
        else if (m_new_word == 1'b1)
            m_axis_last <= 1'b1;
            
    always@(m_axis_valid, data[0], data[1], m_select)
        if (m_axis_valid == 1'b1)
            m_axis_data = (data[m_select][DATA_WIDTH-1:0] > limit) ? limit : data[m_select][DATA_WIDTH-1:0];
        else
            m_axis_data = 'b0;
            
    always@(posedge clk)
        if (s_new_packet == 1'b1)
            s_axis_ready <= 1'b0;
        else if (m_new_packet == 1'b1)
            s_axis_ready <= 1'b1;
endmodule

Pmod-I2S2-Arty-A7-35.srcs/sim_1/new/avc_tb.sv
`timescale 1ns / 1ps
//////////////////////////////////////////////////////////////////////////////////
// Company: 
// Engineer: 
// 
// Create Date: 11/17/2020 10:08:42 PM
// Design Name: 
// Module Name: avc_tb
// Project Name: 
// Target Devices: 
// Tool Versions: 
// Description: 
// 
// Dependencies: 
// 
// Revision:
// Revision 0.01 - File Created
// Additional Comments:
// 
//////////////////////////////////////////////////////////////////////////////////


module avc_tb #(
	parameter SWITCH_WIDTH = 16,
	parameter RESET_POLARITY = 0,
	parameter CLK_HALF_PERIOD = 5,
    parameter TIMEOUT = 10000,
	parameter DATA_WIDTH = 24
	) ();
    
    reg       clk;
    reg [SWITCH_WIDTH-1:0] sw;
    reg       reset;
    wire rst_n;
    assign rst_n = !reset;
    
    reg tx_mclk;
    reg tx_lrck;
    reg tx_sclk;
    reg tx_data;
    reg rx_mclk;
    reg rx_lrck;
    reg rx_sclk;
    reg rx_data;
    
    reg [3:0] Anode_Activate; // anode signals of the 7-segment LED display
    reg [6:0] LED_out;// cathode patterns of the 7-segment LED display
    
    //AXIS SLAVE INTERFACE
    reg [DATA_WIDTH-1:0] s_axis_data = 0;
    reg s_axis_valid;
    wire s_axis_ready;
    reg s_axis_last = 0;
    
    // AXIS MASTER INTERFACE
    reg [DATA_WIDTH-1:0] m_axis_data;
    reg m_axis_valid;
    wire m_axis_ready;
    reg m_axis_last;
    
    reg packet_done = 0;   
    reg [1:0] cnt = 0;        
           
                                        
    always @(posedge clk) begin
        if (s_axis_ready) begin
            s_axis_data <= s_axis_data + 1; 
            s_axis_valid <= 1;
            if (cnt == 2'b0) begin
                s_axis_last <= 1;
            end else begin
                s_axis_last <= 0;
            end
            cnt <= cnt + 1;
//            packet_done <= (cnt == 2'b0);
            //packet_done <= 0;
        end else begin
            s_axis_valid <= 1;
            cnt <= 0;
        end        
    end                                 
    
    assign m_axis_ready = 1;
    
    
//    top top0(.*);
    axis_volume_controller #(SWITCH_WIDTH) avc0(.*);
    
    always begin
        #CLK_HALF_PERIOD;
        // #1;
        clk = !clk; 
    end
    always @(posedge clk) begin
        rx_data = !rx_data;
    end

    initial begin
        $dumpfile("waves.vcd");
        $dumpvars(0,avc_tb);
        #TIMEOUT;
        $finish;
    end

    always @(posedge clk) begin
        sw <= sw + 1;
        #100;
    end
    
    initial begin
        // $monitor("%h %h %h", clk, reset, sw);
        reset = 1;
        sw = 'h1;
        clk = 0;
        rx_data = 0;
        #100ns;
        reset = 0;
        #100ns;
        // sw = 'hFFF;
    end
    
endmodule

waves.vcd
$date
	Sun Nov 29 09:47:03 2020
$end
$version
	Icarus Verilog
$end
$timescale
	1ps
$end
$scope module avc_tb $end
$var wire 1 ! m_axis_ready $end
$var wire 1 " s_axis_ready $end
$var wire 1 # rst_n $end
$var wire 1 $ m_axis_valid $end
$var wire 1 % m_axis_last $end
$var wire 24 & m_axis_data [23:0] $end
$var reg 1 ' clk $end
$var reg 2 ( cnt [1:0] $end
$var reg 1 ) packet_done $end
$var reg 1 * reset $end
$var reg 1 + rx_data $end
$var reg 24 , s_axis_data [23:0] $end
$var reg 1 - s_axis_last $end
$var reg 1 . s_axis_valid $end
$var reg 16 / sw [15:0] $end
$scope module avc0 $end
$var wire 1 ' clk $end
$var wire 24 0 data_out [23:0] $end
$var wire 1 ! m_axis_ready $end
$var wire 1 1 m_select $end
$var wire 1 # rst_n $end
$var wire 24 2 s_axis_data [23:0] $end
$var wire 1 - s_axis_last $end
$var wire 1 . s_axis_valid $end
$var wire 1 3 s_select $end
$var wire 16 4 sw [15:0] $end
$var wire 16 5 sw_sync [15:0] $end
$var wire 7 6 sine_out [6:0] $end
$var wire 1 7 s_new_word $end
$var wire 1 8 s_new_packet $end
$var wire 1 9 m_new_word $end
$var wire 1 : m_new_packet $end
$var wire 24 ; limit [23:0] $end
$var reg 24 < m_axis_data [23:0] $end
$var reg 1 % m_axis_last $end
$var reg 1 $ m_axis_valid $end
$var reg 25 = multiplier [24:0] $end
$var reg 1 " s_axis_ready $end
$var reg 1 > s_new_packet_r $end
$var reg 1 ? s_new_packet_r_q $end
$scope module sine_generator0 $end
$var wire 1 ' clk $end
$var wire 1 # rst_n $end
$var reg 7 @ cnt [6:0] $end
$var reg 7 A out [6:0] $end
$var reg 32 B phase [31:0] $end
$upscope $end
$upscope $end
$upscope $end
$enddefinitions $end
#0
$dumpvars
b0 B
b0 A
b0 @
0?
0>
b0 =
b0 <
b0xxxxxxxxxxxxxxxx ;
0:
09
08
x7
b0 6
bx 5
b1111 4
03
b0 2
01
bz 0
b1111 /
x.
0-
b0 ,
0+
1*
0)
b0 (
0'
b0 &
0%
0$
0#
1"
1!
$end
#5000
18
17
bx =
b1 (
13
1-
1.
b1 ,
b1 2
b10000 /
b10000 4
1+
1'
#10000
0'
#15000
08
07
b10 (
03
0-
b10 ,
b10 2
0"
1>
0+
1'
#20000
0'
#25000
19
bx &
bx <
1?
0>
b1111 ;
b1111 5
1$
b0 (
1+
1'
#30000
0'
#35000
1:
b1 &
b1 <
11
1%
0?
b111100000000 =
b10000 ;
b10000 5
0+
1'
#40000
0'
#45000
09
0:
17
b0 &
b0 <
b1000000000000 =
0$
01
0%
1"
1+
1'
#50000
0'
#55000
18
b1 (
13
1-
b11 ,
b11 2
0+
1'
#60000
0'
#65000
07
08
1>
0"
b10 (
03
0-
b100 ,
b100 2
1+
1'
#70000
0'
#75000
19
b10 &
b10 <
b0 (
1$
1?
0>
0+
1'
#80000
0'
#85000
1:
b11 &
b11 <
0?
11
1%
1+
1'
#90000
0'
#95000
17
0:
09
b0 &
b0 <
1"
01
0%
0$
0+
1'
#100000
0'
1#
0*
#105000
18
b1011 B
b1 @
b1 (
13
1-
b101 ,
b101 2
b10001 /
b10001 4
1+
1'
#110000
0'
#115000
08
07
b10110 B
b10 @
b10 (
03
0-
b110 ,
b110 2
0"
1>
0+
1'
#120000
0'
#125000
19
b100 &
b100 <
b100001 B
b1 6
b1 A
b11 @
1?
0>
1$
b0 (
1+
1'
#130000
0'
#135000
1:
b101 &
b101 <
b101100 B
b11 6
b11 A
b100 @
11
1%
0?
b10001 ;
b10001 5
0+
1'
#140000
0'
#145000
09
0:
17
b0 &
b0 <
b110111 B
b101 @
b1000100000000 =
0$
01
0%
1"
1+
1'
#150000
0'
#155000
18
b1000010 B
b100 6
b100 A
b110 @
b1 (
13
1-
b111 ,
b111 2
0+
1'
#160000
0'
#165000
07
08
b1001101 B
b110 6
b110 A
b111 @
1>
0"
b10 (
03
0-
b1000 ,
b1000 2
1+
1'
#170000
0'
#175000
19
b110 &
b110 <
b1011000 B
b1000 @
b0 (
1$
1?
0>
0+
1'
#180000
0'
#185000
1:
b111 &
b111 <
b1100011 B
b111 6
b111 A
b1001 @
0?
11
1%
1+
1'
#190000
0'
#195000
17
0:
09
b0 &
b0 <
b1101110 B
b1001 6
b1001 A
b1010 @
1"
01
0%
0$
0+
1'
#200000
0'
#205000
18
b1111001 B
b1011 @
b1 (
13
1-
b1001 ,
b1001 2
b10010 /
b10010 4
1+
1'
#210000
0'
#215000
08
07
b10000100 B
b1010 6
b1010 A
b1100 @
b10 (
03
0-
b1010 ,
b1010 2
0"
1>
0+
1'
#220000
0'
#225000
19
b1000 &
b1000 <
b10001111 B
b1100 6
b1100 A
b1101 @
1?
0>
1$
b0 (
1+
1'
#230000
0'
#235000
1:
b1001 &
b1001 <
b10011010 B
b1110 @
11
1%
0?
b10010 ;
b10010 5
0+
1'
#240000
0'
#245000
09
0:
17
b0 &
b0 <
b10100101 B
b1101 6
b1101 A
b1111 @
b1001000000000 =
0$
01
0%
1"
1+
1'
#250000
0'
#255000
18
b10110000 B
b1111 6
b1111 A
b10000 @
b1 (
13
1-
b1011 ,
b1011 2
0+
1'
#260000
0'
#265000
07
08
b10111011 B
b10000 6
b10000 A
b10001 @
1>
0"
b10 (
03
0-
b1100 ,
b1100 2
1+
1'
#270000
0'
#275000
19
b1010 &
b1010 <
b11000110 B
b10010 @
b0 (
1$
1?
0>
0+
1'
#280000
0'
#285000
1:
b1011 &
b1011 <
b11010001 B
b10010 6
b10010 A
b10011 @
0?
11
1%
1+
1'
#290000
0'
#295000
17
0:
09
b0 &
b0 <
b11011100 B
b10011 6
b10011 A
b10100 @
1"
01
0%
0$
0+
1'
#300000
0'
#305000
18
b11100111 B
b10101 @
b1 (
13
1-
b1101 ,
b1101 2
b10011 /
b10011 4
1+
1'
#310000
0'
#315000
08
07
b11110010 B
b10101 6
b10101 A
b10110 @
b10 (
03
0-
b1110 ,
b1110 2
0"
1>
0+
1'
#320000
0'
#325000
19
b1100 &
b1100 <
b11111101 B
b10110 6
b10110 A
b10111 @
1?
0>
1$
b0 (
1+
1'
#330000
0'
#335000
1:
b1101 &
b1101 <
b100001000 B
b11000 @
11
1%
0?
b10011 ;
b10011 5
0+
1'
#340000
0'
#345000
09
0:
17
b0 &
b0 <
b100010011 B
b11000 6
b11000 A
b11001 @
b1001100000000 =
0$
01
0%
1"
1+
1'
#350000
0'
#355000
18
b100011110 B
b11001 6
b11001 A
b11010 @
b1 (
13
1-
b1111 ,
b1111 2
0+
1'
#360000
0'
#365000
07
08
b100101001 B
b11011 @
1>
0"
b10 (
03
0-
b10000 ,
b10000 2
1+
1'
#370000
0'
#375000
19
b1110 &
b1110 <
b100110100 B
b11010 6
b11010 A
b11100 @
b0 (
1$
1?
0>
0+
1'
#380000
0'
#385000
1:
b1111 &
b1111 <
b100111111 B
b11100 6
b11100 A
b11101 @
0?
11
1%
1+
1'
#390000
0'
#395000
17
0:
09
b0 &
b0 <
b101001010 B
b11110 @
1"
01
0%
0$
0+
1'
#400000
0'
#405000
18
b101010101 B
b11101 6
b11101 A
b11111 @
b1 (
13
1-
b10001 ,
b10001 2
b10100 /
b10100 4
1+
1'
#410000
0'
#415000
08
07
b101100000 B
b11111 6
b11111 A
b100000 @
b10 (
03
0-
b10010 ,
b10010 2
0"
1>
0+
1'
#420000
0'
#425000
19
b10000 &
b10000 <
b101101011 B
b100000 6
b100000 A
b100001 @
1?
0>
1$
b0 (
1+
1'
#430000
0'
#435000
1:
b10001 &
b10001 <
b101110110 B
b100010 @
11
1%
0?
b10100 ;
b10100 5
0+
1'
#440000
0'
#445000
09
0:
17
b0 &
b0 <
b110000001 B
b100001 6
b100001 A
b100011 @
b1010000000000 =
0$
01
0%
1"
1+
1'
#450000
0'
#455000
18
b110001100 B
b100011 6
b100011 A
b100100 @
b1 (
13
1-
b10011 ,
b10011 2
0+
1'
#460000
0'
#465000
07
08
b110010111 B
b100101 @
1>
0"
b10 (
03
0-
b10100 ,
b10100 2
1+
1'
#470000
0'
#475000
19
b10010 &
b10010 <
b110100010 B
b100100 6
b100100 A
b100110 @
b0 (
1$
1?
0>
0+
1'
#480000
0'
#485000
1:
b10011 &
b10011 <
b110101101 B
b100101 6
b100101 A
b100111 @
0?
11
1%
1+
1'
#490000
0'
#495000
17
0:
09
b0 &
b0 <
b110111000 B
b101000 @
1"
01
0%
0$
0+
1'
#500000
0'
#505000
18
b111000011 B
b100110 6
b100110 A
b101001 @
b1 (
13
1-
b10101 ,
b10101 2
b10101 /
b10101 4
1+
1'
#510000
0'
#515000
08
07
b111001110 B
b100111 6
b100111 A
b101010 @
b10 (
03
0-
b10110 ,
b10110 2
0"
1>
0+
1'
#520000
0'
#525000
19
b10100 &
b10100 <
b111011001 B
b101011 @
1?
0>
1$
b0 (
1+
1'
#530000
0'
#535000
1:
b10101 &
b10101 <
b111100100 B
b101001 6
b101001 A
b101100 @
11
1%
0?
b10101 ;
b10101 5
0+
1'
#540000
0'
#545000
09
0:
17
b0 &
b0 <
b111101111 B
b101010 6
b101010 A
b101101 @
b1010100000000 =
0$
01
0%
1"
1+
1'
#550000
0'
#555000
18
b111111010 B
b101110 @
b1 (
13
1-
b10111 ,
b10111 2
0+
1'
#560000
0'
#565000
07
08
b1000000101 B
b101011 6
b101011 A
b101111 @
1>
0"
b10 (
03
0-
b11000 ,
b11000 2
1+
1'
#570000
0'
#575000
19
b10101 &
b10101 <
b1000010000 B
b101100 6
b101100 A
b110000 @
b0 (
1$
1?
0>
0+
1'
#580000
0'
#585000
1:
b1000011011 B
b101101 6
b101101 A
b110001 @
0?
11
1%
1+
1'
#590000
0'
#595000
17
0:
09
b0 &
b0 <
b1000100110 B
b110010 @
1"
01
0%
0$
0+
1'
#600000
0'
#605000
18
b1000110001 B
b101110 6
b101110 A
b110011 @
b1 (
13
1-
b11001 ,
b11001 2
b10110 /
b10110 4
1+
1'
#610000
0'
#615000
08
07
b1000111100 B
b101111 6
b101111 A
b110100 @
b10 (
03
0-
b11010 ,
b11010 2
0"
1>
0+
1'
#620000
0'
#625000
19
b10101 &
b10101 <
b1001000111 B
b110101 @
1?
0>
1$
b0 (
1+
1'
#630000
0'
#635000
1:
b10110 &
b10110 <
b1001010010 B
b110000 6
b110000 A
b110110 @
11
1%
0?
b10110 ;
b10110 5
0+
1'
#640000
0'
#645000
09
0:
17
b0 &
b0 <
b1001011101 B
b110001 6
b110001 A
b110111 @
b1011000000000 =
0$
01
0%
1"
1+
1'
#650000
0'
#655000
18
b1001101000 B
b111000 @
b1 (
13
1-
b11011 ,
b11011 2
0+
1'
#660000
0'
#665000
07
08
b1001110011 B
b110010 6
b110010 A
b111001 @
1>
0"
b10 (
03
0-
b11100 ,
b11100 2
1+
1'
#670000
0'
#675000
19
b10110 &
b10110 <
b1001111110 B
b110011 6
b110011 A
b111010 @
b0 (
1$
1?
0>
0+
1'
#680000
0'
#685000
1:
b1010001001 B
b111011 @
0?
11
1%
1+
1'
#690000
0'
#695000
17
0:
09
b0 &
b0 <
b1010010100 B
b110100 6
b110100 A
b111100 @
1"
01
0%
0$
0+
1'
#700000
0'
#705000
18
b1010011111 B
b110101 6
b110101 A
b111101 @
b1 (
13
1-
b11101 ,
b11101 2
b10111 /
b10111 4
1+
1'
#710000
0'
#715000
08
07
b1010101010 B
b111110 @
b10 (
03
0-
b11110 ,
b11110 2
0"
1>
0+
1'
#720000
0'
#725000
19
b10110 &
b10110 <
b1010110101 B
b110110 6
b110110 A
b111111 @
1?
0>
1$
b0 (
1+
1'
#730000
0'
#735000
1:
b10111 &
b10111 <
b1011000000 B
b1000000 @
11
1%
0?
b10111 ;
b10111 5
0+
1'
#740000
0'
#745000
09
0:
17
b0 &
b0 <
b1011001011 B
b110111 6
b110111 A
b1000001 @
b1011100000000 =
0$
01
0%
1"
1+
1'
#750000
0'
#755000
18
b1011010110 B
b1000010 @
b1 (
13
1-
b11111 ,
b11111 2
0+
1'
#760000
0'
#765000
07
08
b1011100001 B
b111000 6
b111000 A
b1000011 @
1>
0"
b10 (
03
0-
b100000 ,
b100000 2
1+
1'
#770000
0'
#775000
19
b10111 &
b10111 <
b1011101100 B
b1000100 @
b0 (
1$
1?
0>
0+
1'
#780000
0'
#785000
1:
b1011110111 B
b1000101 @
0?
11
1%
1+
1'
#790000
0'
#795000
17
0:
09
b0 &
b0 <
b1100000010 B
b111001 6
b111001 A
b1000110 @
1"
01
0%
0$
0+
1'
#800000
0'
#805000
18
b1100001101 B
b111010 6
b111010 A
b1000111 @
b1 (
13
1-
b100001 ,
b100001 2
b11000 /
b11000 4
1+
1'
#810000
0'
#815000
08
07
b1100011000 B
b1001000 @
b10 (
03
0-
b100010 ,
b100010 2
0"
1>
0+
1'
#820000
0'
#825000
19
b10111 &
b10111 <
b1100100011 B
b1001001 @
1?
0>
1$
b0 (
1+
1'
#830000
0'
#835000
1:
b11000 &
b11000 <
b1100101110 B
b111011 6
b111011 A
b1001010 @
11
1%
0?
b11000 ;
b11000 5
0+
1'
#840000
0'
#845000
09
0:
17
b0 &
b0 <
b1100111001 B
b1001011 @
b1100000000000 =
0$
01
0%
1"
1+
1'
#850000
0'
#855000
18
b1101000100 B
b1001100 @
b1 (
13
1-
b100011 ,
b100011 2
0+
1'
#860000
0'
#865000
07
08
b1101001111 B
b111100 6
b111100 A
b1001101 @
1>
0"
b10 (
03
0-
b100100 ,
b100100 2
1+
1'
#870000
0'
#875000
19
b11000 &
b11000 <
b1101011010 B
b1001110 @
b0 (
1$
1?
0>
0+
1'
#880000
0'
#885000
1:
b1101100101 B
b1001111 @
0?
11
1%
1+
1'
#890000
0'
#895000
17
0:
09
b0 &
b0 <
b1101110000 B
b111101 6
b111101 A
b1010000 @
1"
01
0%
0$
0+
1'
#900000
0'
#905000
18
b1101111011 B
b1010001 @
b1 (
13
1-
b100101 ,
b100101 2
b11001 /
b11001 4
1+
1'
#910000
0'
#915000
08
07
b1110000110 B
b1010010 @
b10 (
03
0-
b100110 ,
b100110 2
0"
1>
0+
1'
#920000
0'
#925000
19
b11000 &
b11000 <
b1110010001 B
b1010011 @
1?
0>
1$
b0 (
1+
1'
#930000
0'
#935000
1:
b11001 &
b11001 <
b1110011100 B
b111110 6
b111110 A
b1010100 @
11
1%
0?
b11001 ;
b11001 5
0+
1'
#940000
0'
#945000
09
0:
17
b0 &
b0 <
b1110100111 B
b1010101 @
b1100100000000 =
0$
01
0%
1"
1+
1'
#950000
0'
#955000
18
b1110110010 B
b1010110 @
b1 (
13
1-
b100111 ,
b100111 2
0+
1'
#960000
0'
#965000
07
08
b1110111101 B
b1010111 @
1>
0"
b10 (
03
0-
b101000 ,
b101000 2
1+
1'
#970000
0'
#975000
19
b11001 &
b11001 <
b1111001000 B
b1011000 @
b0 (
1$
1?
0>
0+
1'
#980000
0'
#985000
1:
b1111010011 B
b1011001 @
0?
11
1%
1+
1'
#990000
0'
#995000
17
0:
09
b0 &
b0 <
b1111011110 B
b1011010 @
1"
01
0%
0$
0+
1'
#1000000
0'
#1005000
18
b1111101001 B
b1011011 @
b1 (
13
1-
b101001 ,
b101001 2
b11010 /
b11010 4
1+
1'
#1010000
0'
#1015000
08
07
b1111110100 B
b1011100 @
b10 (
03
0-
b101010 ,
b101010 2
0"
1>
0+
1'
#1020000
0'
#1025000
19
b11001 &
b11001 <
b1111111111 B
b1011101 @
1?
0>
1$
b0 (
1+
1'
#1030000
0'
#1035000
1:
b11010 &
b11010 <
b10000001010 B
b1011110 @
11
1%
0?
b11010 ;
b11010 5
0+
1'
#1040000
0'
#1045000
09
0:
17
b0 &
b0 <
b10000010101 B
b111111 6
b111111 A
b1011111 @
b1101000000000 =
0$
01
0%
1"
1+
1'
#1050000
0'
#1055000
18
b10000100000 B
b111110 6
b111110 A
b1100000 @
b1 (
13
1-
b101011 ,
b101011 2
0+
1'
#1060000
0'
#1065000
07
08
b10000101011 B
b1100001 @
1>
0"
b10 (
03
0-
b101100 ,
b101100 2
1+
1'
#1070000
0'
#1075000
19
b11010 &
b11010 <
b10000110110 B
b1100010 @
b0 (
1$
1?
0>
0+
1'
#1080000
0'
#1085000
1:
b10001000001 B
b1100011 @
0?
11
1%
1+
1'
#1090000
0'
#1095000
17
0:
09
b0 &
b0 <
b10001001100 B
b1100100 @
1"
01
0%
0$
0+
1'
#1100000
0'
#1105000
18
b10001010111 B
b1100101 @
b1 (
13
1-
b101101 ,
b101101 2
b11011 /
b11011 4
1+
1'
#1110000
0'
#1115000
08
07
b10001100010 B
b1100110 @
b10 (
03
0-
b101110 ,
b101110 2
0"
1>
0+
1'
#1120000
0'
#1125000
19
b11010 &
b11010 <
b10001101101 B
b1100111 @
1?
0>
1$
b0 (
1+
1'
#1130000
0'
#1135000
1:
b11011 &
b11011 <
b10001111000 B
b1101000 @
11
1%
0?
b11011 ;
b11011 5
0+
1'
#1140000
0'
#1145000
09
0:
17
b0 &
b0 <
b10010000011 B
b1101001 @
b1101100000000 =
0$
01
0%
1"
1+
1'
#1150000
0'
#1155000
18
b10010001110 B
b111101 6
b111101 A
b1101010 @
b1 (
13
1-
b101111 ,
b101111 2
0+
1'
#1160000
0'
#1165000
07
08
b10010011001 B
b1101011 @
1>
0"
b10 (
03
0-
b110000 ,
b110000 2
1+
1'
#1170000
0'
#1175000
19
b11011 &
b11011 <
b10010100100 B
b1101100 @
b0 (
1$
1?
0>
0+
1'
#1180000
0'
#1185000
1:
b10010101111 B
b1101101 @
0?
11
1%
1+
1'
#1190000
0'
#1195000
17
0:
09
b0 &
b0 <
b10010111010 B
b1101110 @
1"
01
0%
0$
0+
1'
#1200000
0'
#1205000
18
b10011000101 B
b111100 6
b111100 A
b1101111 @
b1 (
13
1-
b110001 ,
b110001 2
b11100 /
b11100 4
1+
1'
#1210000
0'
#1215000
08
07
b10011010000 B
b1110000 @
b10 (
03
0-
b110010 ,
b110010 2
0"
1>
0+
1'
#1220000
0'
#1225000
19
b11011 &
b11011 <
b10011011011 B
b111011 6
b111011 A
b1110001 @
1?
0>
1$
b0 (
1+
1'
#1230000
0'
#1235000
1:
b11100 &
b11100 <
b10011100110 B
b1110010 @
11
1%
0?
b11100 ;
b11100 5
0+
1'
#1240000
0'
#1245000
09
0:
17
b0 &
b0 <
b10011110001 B
b1110011 @
b1110000000000 =
0$
01
0%
1"
1+
1'
#1250000
0'
#1255000
18
b10011111100 B
b111010 6
b111010 A
b1110100 @
b1 (
13
1-
b110011 ,
b110011 2
0+
1'
#1260000
0'
#1265000
07
08
b10100000111 B
b1110101 @
1>
0"
b10 (
03
0-
b110100 ,
b110100 2
1+
1'
#1270000
0'
#1275000
19
b11100 &
b11100 <
b10100010010 B
b1110110 @
b0 (
1$
1?
0>
0+
1'
#1280000
0'
#1285000
1:
b10100011101 B
b111001 6
b111001 A
b1110111 @
0?
11
1%
1+
1'
#1290000
0'
#1295000
17
0:
09
b0 &
b0 <
b10100101000 B
b1111000 @
1"
01
0%
0$
0+
1'
#1300000
0'
#1305000
18
b10100110011 B
b111000 6
b111000 A
b1111001 @
b1 (
13
1-
b110101 ,
b110101 2
b11101 /
b11101 4
1+
1'
#1310000
0'
#1315000
08
07
b10100111110 B
b1111010 @
b10 (
03
0-
b110110 ,
b110110 2
0"
1>
0+
1'
#1320000
0'
#1325000
19
b11100 &
b11100 <
b10101001001 B
b1111011 @
1?
0>
1$
b0 (
1+
1'
#1330000
0'
#1335000
1:
b11101 &
b11101 <
b10101010100 B
b110111 6
b110111 A
b1111100 @
11
1%
0?
b11101 ;
b11101 5
0+
1'
#1340000
0'
#1345000
09
0:
17
b0 &
b0 <
b10101011111 B
b110110 6
b110110 A
b1111101 @
b1110100000000 =
0$
01
0%
1"
1+
1'
#1350000
0'
#1355000
18
b10101101010 B
b1111110 @
b1 (
13
1-
b110111 ,
b110111 2
0+
1'
#1360000
0'
#1365000
07
08
b10101110101 B
b1111111 @
1>
0"
b10 (
03
0-
b111000 ,
b111000 2
1+
1'
#1370000
0'
#1375000
19
b11101 &
b11101 <
b10110000000 B
b110101 6
b110101 A
b0 @
b0 (
1$
1?
0>
0+
1'
#1380000
0'
#1385000
1:
b10110001011 B
b110100 6
b110100 A
b1 @
0?
11
1%
1+
1'
#1390000
0'
#1395000
17
0:
09
b0 &
b0 <
b10110010110 B
b10 @
1"
01
0%
0$
0+
1'
#1400000
0'
#1405000
18
b10110100001 B
b110011 6
b110011 A
b11 @
b1 (
13
1-
b111001 ,
b111001 2
b11110 /
b11110 4
1+
1'
#1410000
0'
#1415000
08
07
b10110101100 B
b110010 6
b110010 A
b100 @
b10 (
03
0-
b111010 ,
b111010 2
0"
1>
0+
1'
#1420000
0'
#1425000
19
b11101 &
b11101 <
b10110110111 B
b101 @
1?
0>
1$
b0 (
1+
1'
#1430000
0'
#1435000
1:
b11110 &
b11110 <
b10111000010 B
b110001 6
b110001 A
b110 @
11
1%
0?
b11110 ;
b11110 5
0+
1'
#1440000
0'
